pyqt_templates/__init__.py
pyqt_templates/fonts.py
pyqt_templates/from_t8.py
pyqt_templates/gui.py
pyqt_templates/highlighter.py
pyqt_templates/signals.py
pyqt_templates/th.py
pyqt_templates/tm.py
pyqt_templates/zero_stuff.py
pyqt_templates-0.1.6.dist-info/LICENSE
pyqt_templates-0.1.6.dist-info/METADATA
pyqt_templates-0.1.6.dist-info/WHEEL
pyqt_templates-0.1.6.dist-info/top_level.txt
pyqt_templates-0.1.6.dist-info/RECORD
