Metadata-Version: 2.1
Name: pyqt_templates
Version: 0.1.6
Summary: pyqt help examples and some other useful objects (overloaded pyqt classes)
Home-page: https://github.com/centroid457/
Author: Andrei Starichenko
Author-email: centroid@mail.ru
Project-URL: Source, https://github.com/centroid457/pyqt_templates
Keywords: pyqt,pyqt templates,pyqt guide,pyqt usage,pyqt examples,pyqt usage examples,pyqt help,pyqt help examples,pyqt signals,pyqt highlighter
Classifier: Topic :: Software Development :: Libraries :: Python Modules
Classifier: License :: OSI Approved :: MIT License
Classifier: Programming Language :: Python
Classifier: Programming Language :: Python :: 3 :: Only
Classifier: Programming Language :: Python :: 3.11
Classifier: Operating System :: OS Independent
Classifier: Intended Audience :: Developers
Classifier: Natural Language :: English
Classifier: Typing :: Typed
Requires-Python: >=3.6
License-File: LICENSE
